pymongolite/__init__.py
pymongolite/backend/__init__.py
pymongolite/backend/command.py
pymongolite/backend/document.py
pymongolite/backend/exceptions.py
pymongolite/backend/execution_engine/__init__.py
pymongolite/backend/execution_engine/base_engine.py
pymongolite/backend/execution_engine/chunked_engine.py
pymongolite/backend/execution_engine/cursor.py
pymongolite/backend/execution_engine/exceptions.py
pymongolite/backend/execution_engine/utils.py
pymongolite/backend/indexing_engine/__init__.py
pymongolite/backend/indexing_engine/base_engine.py
pymongolite/backend/indexing_engine/base_index.py
pymongolite/backend/indexing_engine/index_metadata.py
pymongolite/backend/indexing_engine/index_types/__init__.py
pymongolite/backend/indexing_engine/index_types/sorted_list_basic_index.py
pymongolite/backend/indexing_engine/v1_engine.py
pymongolite/backend/objectid.py
pymongolite/backend/read_instructions.py
pymongolite/backend/session.py
pymongolite/backend/storage_engine/__init__.py
pymongolite/backend/storage_engine/base_engine.py
pymongolite/backend/storage_engine/files_engine.py
pymongolite/backend/storage_engine/insert_instruction.py
pymongolite/backend/storage_engine/update_instructions.py
pymongolite/backend/utils.py
pymongolite/client.py
pymongolite/collection.py
pymongolite/database.py
pymongolite/exceptions.py
pymongolite-0.1.7.dist-info/WHEEL
pymongolite-0.1.7.dist-info/METADATA
pymongolite-0.1.7.dist-info/RECORD
