Metadata-Version: 2.1
Name: pymongolite
Version: 0.1.7
Summary: 
Home-page: https://github.com/hvuhsg/mongolite
Keywords: mongo,python,lite,local,simple,pymongo,NoSQL,db,database
Author: yehoyada
Author-email: yehoyada.sht@gmail.com
Requires-Python: >=3.8,<4.0
Classifier: Programming Language :: Python :: 3
Classifier: Programming Language :: Python :: 3.10
Classifier: Programming Language :: Python :: 3.8
Classifier: Programming Language :: Python :: 3.9
Requires-Dist: sortedcontainers (>=2.4.0,<3.0.0)
Project-URL: Repository, https://github.com/hvuhsg/mongolite
